{
  "$schema": "./.sitecore/schemas/RootConfigurationFile.schema.json",
  "modules": [
    "src/*.module.json",
    "src/serialization/Foundation/*/*.module.json",
    "src/serialization/Feature/*/*.module.json",
    "src/serialization/Project/*/*.module.json",
    "npm:@constellation4sitecore/foundation-labels@0.1.1-beta.16",
    "npm:@constellation4sitecore/feature-navigation@0.1.1-beta.16"
  ],
  "plugins": [
    "Sitecore.DevEx.Extensibility.Serialization@5.1.25",
    "Sitecore.DevEx.Extensibility.Publishing@5.1.25",
    "Sitecore.DevEx.Extensibility.Indexing@5.1.25",
    "Sitecore.DevEx.Extensibility.ResourcePackage@5.1.25",
    "Sitecore.DevEx.Extensibility.XMCloud@1.1.16"
  ],
  "serialization": {
    "defaultMaxRelativeItemPathLength": 100,
    "defaultModuleRelativeSerializationPath": "items",
    "removeOrphansForRoles": true,
    "continueOnItemFailure": false,
    "excludedFields": []
  },
  "settings": {
    "telemetryEnabled": false,
    "versionComparingEnabled": true
  }
}